{".class":"MypyFile","_fullname":"streamlit.elements.lib.column_types","future_import_flags":["annotations"],"is_partial_stub_package":false,"is_stub":false,"names":{".class":"SymbolTable","AreaChartColumn":{".class":"SymbolTableNode","kind":"Gdef","node":{".class":"Decorator","func":{".class":"FuncDef","abstract_status":0,"arg_kinds":[1,5,5,5,5],"arg_names":["label","width","help","y_min","y_max"],"dataclass_transform_spec":null,"flags":["is_decorated"],"fullname":"streamlit.elements.lib.column_types.AreaChartColumn","name":"AreaChartColumn","type":{".class":"CallableType","arg_kinds":[1,5,5,5,5],"arg_names":["label","width","help","y_min","y_max"],"arg_types":[{".class":"UnionType","items":["builtins.str",{".class":"NoneType"}]},{".class":"UnionType","items":[{".class":"TypeAliasType","args":[],"type_ref":"streamlit.elements.lib.column_types.ColumnWidth"},{".class":"NoneType"}]},{".class":"UnionType","items":["builtins.str",{".class":"NoneType"}]},{".class":"UnionType","items":["builtins.int","builtins.float",{".class":"NoneType"}]},{".class":"UnionType","items":["builtins.int","builtins.float",{".class":"NoneType"}]}],"bound_args":[],"def_extras":{"first_arg":null},"fallback":"builtins.function","from_concatenate":false,"implicit":false,"imprecise_arg_kinds":false,"is_ellipsis_args":false,"name":"AreaChartColumn","ret_type":{".class":"TypeAliasType","args":[],"type_ref":"streamlit.elements.lib.column_types.ColumnConfig"},"type_guard":null,"type_is":null,"unpack_kwargs":false,"variables":[]}},"is_overload":false,"var":{".class":"Var","flags":["is_ready","is_inferred"],"fullname":"streamlit.elements.lib.column_types.AreaChartColumn","name":"AreaChartColumn","type":{".class":"CallableType","arg_kinds":[1,5,5,5,5],"arg_names":["label","width","help","y_min","y_max"],"arg_types":[{".class":"UnionType","items":["builtins.str",{".class":"NoneType"}]},{".class":"UnionType","items":[{".class":"TypeAliasType","args":[],"type_ref":"streamlit.elements.lib.column_types.ColumnWidth"},{".class":"NoneType"}]},{".class":"UnionType","items":["builtins.str",{".class":"NoneType"}]},{".class":"UnionType","items":["builtins.int","builtins.float",{".class":"NoneType"}]},{".class":"UnionType","items":["builtins.int","builtins.float",{".class":"NoneType"}]}],"bound_args":[],"def_extras":{"first_arg":null},"fallback":"builtins.function","from_concatenate":false,"implicit":false,"imprecise_arg_kinds":false,"is_ellipsis_args":false,"name":"AreaChartColumn","ret_type":{".class":"TypeAliasType","args":[],"type_ref":"streamlit.elements.lib.column_types.ColumnConfig"},"type_guard":null,"type_is":null,"unpack_kwargs":false,"variables":[]}}}},"AreaChartColumnConfig":{".class":"SymbolTableNode","kind":"Gdef","node":{".class":"TypeInfo","_promote":[],"abstract_attributes":[],"alt_promote":null,"bases":["typing._TypedDict"],"dataclass_transform_spec":null,"declared_metaclass":null,"defn":{".class":"ClassDef","fullname":"streamlit.elements.lib.column_types.AreaChartColumnConfig","name":"AreaChartColumnConfig","type_vars":[]},"deletable_attributes":[],"flags":[],"fullname":"streamlit.elements.lib.column_types.AreaChartColumnConfig","has_param_spec_type":false,"metaclass_type":null,"metadata":{},"module_name":"streamlit.elements.lib.column_types","mro":["streamlit.elements.lib.column_types.AreaChartColumnConfig","typing._TypedDict","typing.Mapping","typing.Collection","typing.Iterable","typing.Container","builtins.object"],"names":{".class":"SymbolTable"},"self_type":null,"slots":null,"tuple_type":null,"type_vars":[],"typeddict_type":{".class":"TypedDictType","fallback":"typing._TypedDict","items":[["type",{".class":"LiteralType","fallback":"builtins.str","value":"area_chart"}],["y_min",{".class":"UnionType","items":["builtins.int","builtins.float",{".class":"NoneType"}]}],["y_max",{".class":"UnionType","items":["builtins.int","builtins.float",{".class":"NoneType"}]}]],"required_keys":["type"]}}},"BarChartColumn":{".class":"SymbolTableNode","kind":"Gdef","node":{".class":"Decorator","func":{".class":"FuncDef","abstract_status":0,"arg_kinds":[1,5,5,5,5],"arg_names":["label","width","help","y_min","y_max"],"dataclass_transform_spec":null,"flags":["is_decorated"],"fullname":"streamlit.elements.lib.column_types.BarChartColumn","name":"BarChartColumn","type":{".class":"CallableType","arg_kinds":[1,5,5,5,5],"arg_names":["label","width","help","y_min","y_max"],"arg_types":[{".class":"UnionType","items":["builtins.str",{".class":"NoneType"}]},{".class":"UnionType","items":[{".class":"TypeAliasType","args":[],"type_ref":"streamlit.elements.lib.column_types.ColumnWidth"},{".class":"NoneType"}]},{".class":"UnionType","items":["builtins.str",{".class":"NoneType"}]},{".class":"UnionType","items":["builtins.int","builtins.float",{".class":"NoneType"}]},{".class":"UnionType","items":["builtins.int","builtins.float",{".class":"NoneType"}]}],"bound_args":[],"def_extras":{"first_arg":null},"fallback":"builtins.function","from_concatenate":false,"implicit":false,"imprecise_arg_kinds":false,"is_ellipsis_args":false,"name":"BarChartColumn","ret_type":{".class":"TypeAliasType","args":[],"type_ref":"streamlit.elements.lib.column_types.ColumnConfig"},"type_guard":null,"type_is":null,"unpack_kwargs":false,"variables":[]}},"is_overload":false,"var":{".class":"Var","flags":["is_ready","is_inferred"],"fullname":"streamlit.elements.lib.column_types.BarChartColumn","name":"BarChartColumn","type":{".class":"CallableType","arg_kinds":[1,5,5,5,5],"arg_names":["label","width","help","y_min","y_max"],"arg_types":[{".class":"UnionType","items":["builtins.str",{".class":"NoneType"}]},{".class":"UnionType","items":[{".class":"TypeAliasType","args":[],"type_ref":"streamlit.elements.lib.column_types.ColumnWidth"},{".class":"NoneType"}]},{".class":"UnionType","items":["builtins.str",{".class":"NoneType"}]},{".class":"UnionType","items":["builtins.int","builtins.float",{".class":"NoneType"}]},{".class":"UnionType","items":["builtins.int","builtins.float",{".class":"NoneType"}]}],"bound_args":[],"def_extras":{"first_arg":null},"fallback":"builtins.function","from_concatenate":false,"implicit":false,"imprecise_arg_kinds":false,"is_ellipsis_args":false,"name":"BarChartColumn","ret_type":{".class":"TypeAliasType","args":[],"type_ref":"streamlit.elements.lib.column_types.ColumnConfig"},"type_guard":null,"type_is":null,"unpack_kwargs":false,"variables":[]}}}},"BarChartColumnConfig":{".class":"SymbolTableNode","kind":"Gdef","node":{".class":"TypeInfo","_promote":[],"abstract_attributes":[],"alt_promote":null,"bases":["typing._TypedDict"],"dataclass_transform_spec":null,"declared_metaclass":null,"defn":{".class":"ClassDef","fullname":"streamlit.elements.lib.column_types.BarChartColumnConfig","name":"BarChartColumnConfig","type_vars":[]},"deletable_attributes":[],"flags":[],"fullname":"streamlit.elements.lib.column_types.BarChartColumnConfig","has_param_spec_type":false,"metaclass_type":null,"metadata":{},"module_name":"streamlit.elements.lib.column_types","mro":["streamlit.elements.lib.column_types.BarChartColumnConfig","typing._TypedDict","typing.Mapping","typing.Collection","typing.Iterable","typing.Container","builtins.object"],"names":{".class":"SymbolTable"},"self_type":null,"slots":null,"tuple_type":null,"type_vars":[],"typeddict_type":{".class":"TypedDictType","fallback":"typing._TypedDict","items":[["type",{".class":"LiteralType","fallback":"builtins.str","value":"bar_chart"}],["y_min",{".class":"UnionType","items":["builtins.int","builtins.float",{".class":"NoneType"}]}],["y_max",{".class":"UnionType","items":["builtins.int","builtins.float",{".class":"NoneType"}]}]],"required_keys":["type"]}}},"CheckboxColumn":{".class":"SymbolTableNode","kind":"Gdef","node":{".class":"Decorator","func":{".class":"FuncDef","abstract_status":0,"arg_kinds":[1,5,5,5,5,5],"arg_names":["label","width","help","disabled","required","default"],"dataclass_transform_spec":null,"flags":["is_decorated"],"fullname":"streamlit.elements.lib.column_types.CheckboxColumn","name":"CheckboxColumn","type":{".class":"CallableType","arg_kinds":[1,5,5,5,5,5],"arg_names":["label","width","help","disabled","required","default"],"arg_types":[{".class":"UnionType","items":["builtins.str",{".class":"NoneType"}]},{".class":"UnionType","items":[{".class":"TypeAliasType","args":[],"type_ref":"streamlit.elements.lib.column_types.ColumnWidth"},{".class":"NoneType"}]},{".class":"UnionType","items":["builtins.str",{".class":"NoneType"}]},{".class":"UnionType","items":["builtins.bool",{".class":"NoneType"}]},{".class":"UnionType","items":["builtins.bool",{".class":"NoneType"}]},{".class":"UnionType","items":["builtins.bool",{".class":"NoneType"}]}],"bound_args":[],"def_extras":{"first_arg":null},"fallback":"builtins.function","from_concatenate":false,"implicit":false,"imprecise_arg_kinds":false,"is_ellipsis_args":false,"name":"CheckboxColumn","ret_type":{".class":"TypeAliasType","args":[],"type_ref":"streamlit.elements.lib.column_types.ColumnConfig"},"type_guard":null,"type_is":null,"unpack_kwargs":false,"variables":[]}},"is_overload":false,"var":{".class":"Var","flags":["is_ready","is_inferred"],"fullname":"streamlit.elements.lib.column_types.CheckboxColumn","name":"CheckboxColumn","type":{".class":"CallableType","arg_kinds":[1,5,5,5,5,5],"arg_names":["label","width","help","disabled","required","default"],"arg_types":[{".class":"UnionType","items":["builtins.str",{".class":"NoneType"}]},{".class":"UnionType","items":[{".class":"TypeAliasType","args":[],"type_ref":"streamlit.elements.lib.column_types.ColumnWidth"},{".class":"NoneType"}]},{".class":"UnionType","items":["builtins.str",{".class":"NoneType"}]},{".class":"UnionType","items":["builtins.bool",{".class":"NoneType"}]},{".class":"UnionType","items":["builtins.bool",{".class":"NoneType"}]},{".class":"UnionType","items":["builtins.bool",{".class":"NoneType"}]}],"bound_args":[],"def_extras":{"first_arg":null},"fallback":"builtins.function","from_concatenate":false,"implicit":false,"imprecise_arg_kinds":false,"is_ellipsis_args":false,"name":"CheckboxColumn","ret_type":{".class":"TypeAliasType","args":[],"type_ref":"streamlit.elements.lib.column_types.ColumnConfig"},"type_guard":null,"type_is":null,"unpack_kwargs":false,"variables":[]}}}},"CheckboxColumnConfig":{".class":"SymbolTableNode","kind":"Gdef","node":{".class":"TypeInfo","_promote":[],"abstract_attributes":[],"alt_promote":null,"bases":["typing._TypedDict"],"dataclass_transform_spec":null,"declared_metaclass":null,"defn":{".class":"ClassDef","fullname":"streamlit.elements.lib.column_types.CheckboxColumnConfig","name":"CheckboxColumnConfig","type_vars":[]},"deletable_attributes":[],"flags":[],"fullname":"streamlit.elements.lib.column_types.CheckboxColumnConfig","has_param_spec_type":false,"metaclass_type":null,"metadata":{},"module_name":"streamlit.elements.lib.column_types","mro":["streamlit.elements.lib.column_types.CheckboxColumnConfig","typing._TypedDict","typing.Mapping","typing.Collection","typing.Iterable","typing.Container","builtins.object"],"names":{".class":"SymbolTable"},"self_type":null,"slots":null,"tuple_type":null,"type_vars":[],"typeddict_type":{".class":"TypedDictType","fallback":"typing._TypedDict","items":[["type",{".class":"LiteralType","fallback":"builtins.str","value":"checkbox"}]],"required_keys":["type"]}}},"Column":{".class":"SymbolTableNode","kind":"Gdef","node":{".class":"Decorator","func":{".class":"FuncDef","abstract_status":0,"arg_kinds":[1,5,5,5,5],"arg_names":["label","width","help","disabled","required"],"dataclass_transform_spec":null,"flags":["is_decorated"],"fullname":"streamlit.elements.lib.column_types.Column","name":"Column","type":{".class":"CallableType","arg_kinds":[1,5,5,5,5],"arg_names":["label","width","help","disabled","required"],"arg_types":[{".class":"UnionType","items":["builtins.str",{".class":"NoneType"}]},{".class":"UnionType","items":[{".class":"TypeAliasType","args":[],"type_ref":"streamlit.elements.lib.column_types.ColumnWidth"},{".class":"NoneType"}]},{".class":"UnionType","items":["builtins.str",{".class":"NoneType"}]},{".class":"UnionType","items":["builtins.bool",{".class":"NoneType"}]},{".class":"UnionType","items":["builtins.bool",{".class":"NoneType"}]}],"bound_args":[],"def_extras":{"first_arg":null},"fallback":"builtins.function","from_concatenate":false,"implicit":false,"imprecise_arg_kinds":false,"is_ellipsis_args":false,"name":"Column","ret_type":{".class":"TypeAliasType","args":[],"type_ref":"streamlit.elements.lib.column_types.ColumnConfig"},"type_guard":null,"type_is":null,"unpack_kwargs":false,"variables":[]}},"is_overload":false,"var":{".class":"Var","flags":["is_ready","is_inferred"],"fullname":"streamlit.elements.lib.column_types.Column","name":"Column","type":{".class":"CallableType","arg_kinds":[1,5,5,5,5],"arg_names":["label","width","help","disabled","required"],"arg_types":[{".class":"UnionType","items":["builtins.str",{".class":"NoneType"}]},{".class":"UnionType","items":[{".class":"TypeAliasType","args":[],"type_ref":"streamlit.elements.lib.column_types.ColumnWidth"},{".class":"NoneType"}]},{".class":"UnionType","items":["builtins.str",{".class":"NoneType"}]},{".class":"UnionType","items":["builtins.bool",{".class":"NoneType"}]},{".class":"UnionType","items":["builtins.bool",{".class":"NoneType"}]}],"bound_args":[],"def_extras":{"first_arg":null},"fallback":"builtins.function","from_concatenate":false,"implicit":false,"imprecise_arg_kinds":false,"is_ellipsis_args":false,"name":"Column","ret_type":{".class":"TypeAliasType","args":[],"type_ref":"streamlit.elements.lib.column_types.ColumnConfig"},"type_guard":null,"type_is":null,"unpack_kwargs":false,"variables":[]}}}},"ColumnConfig":{".class":"SymbolTableNode","kind":"Gdef","node":{".class":"TypeInfo","_promote":[],"abstract_attributes":[],"alt_promote":null,"bases":["typing._TypedDict"],"dataclass_transform_spec":null,"declared_metaclass":null,"defn":{".class":"ClassDef","fullname":"streamlit.elements.lib.column_types.ColumnConfig","name":"ColumnConfig","type_vars":[]},"deletable_attributes":[],"flags":[],"fullname":"streamlit.elements.lib.column_types.ColumnConfig","has_param_spec_type":false,"metaclass_type":null,"metadata":{},"module_name":"streamlit.elements.lib.column_types","mro":["streamlit.elements.lib.column_types.ColumnConfig","typing._TypedDict","typing.Mapping","typing.Collection","typing.Iterable","typing.Container","builtins.object"],"names":{".class":"SymbolTable"},"self_type":null,"slots":null,"tuple_type":null,"type_vars":[],"typeddict_type":{".class":"TypedDictType","fallback":"typing._TypedDict","items":[["label",{".class":"UnionType","items":["builtins.str",{".class":"NoneType"}]}],["width",{".class":"UnionType","items":[{".class":"TypeAliasType","args":[],"type_ref":"streamlit.elements.lib.column_types.ColumnWidth"},{".class":"NoneType"}]}],["help",{".class":"UnionType","items":["builtins.str",{".class":"NoneType"}]}],["hidden",{".class":"UnionType","items":["builtins.bool",{".class":"NoneType"}]}],["disabled",{".class":"UnionType","items":["builtins.bool",{".class":"NoneType"}]}],["required",{".class":"UnionType","items":["builtins.bool",{".class":"NoneType"}]}],["default",{".class":"UnionType","items":["builtins.str","builtins.bool","builtins.int","builtins.float",{".class":"NoneType"}]}],["alignment",{".class":"UnionType","items":[{".class":"LiteralType","fallback":"builtins.str","value":"left"},{".class":"LiteralType","fallback":"builtins.str","value":"center"},{".class":"LiteralType","fallback":"builtins.str","value":"right"},{".class":"NoneType"}]}],["type_config",{".class":"UnionType","items":[{".class":"TypeAliasType","args":[],"type_ref":"streamlit.elements.lib.column_types.NumberColumnConfig"},{".class":"TypeAliasType","args":[],"type_ref":"streamlit.elements.lib.column_types.TextColumnConfig"},{".class":"TypeAliasType","args":[],"type_ref":"streamlit.elements.lib.column_types.CheckboxColumnConfig"},{".class":"TypeAliasType","args":[],"type_ref":"streamlit.elements.lib.column_types.SelectboxColumnConfig"},{".class":"TypeAliasType","args":[],"type_ref":"streamlit.elements.lib.column_types.LinkColumnConfig"},{".class":"TypeAliasType","args":[],"type_ref":"streamlit.elements.lib.column_types.ListColumnConfig"},{".class":"TypeAliasType","args":[],"type_ref":"streamlit.elements.lib.column_types.DatetimeColumnConfig"},{".class":"TypeAliasType","args":[],"type_ref":"streamlit.elements.lib.column_types.DateColumnConfig"},{".class":"TypeAliasType","args":[],"type_ref":"streamlit.elements.lib.column_types.TimeColumnConfig"},{".class":"TypeAliasType","args":[],"type_ref":"streamlit.elements.lib.column_types.ProgressColumnConfig"},{".class":"TypeAliasType","args":[],"type_ref":"streamlit.elements.lib.column_types.LineChartColumnConfig"},{".class":"TypeAliasType","args":[],"type_ref":"streamlit.elements.lib.column_types.BarChartColumnConfig"},{".class":"TypeAliasType","args":[],"type_ref":"streamlit.elements.lib.column_types.AreaChartColumnConfig"},{".class":"TypeAliasType","args":[],"type_ref":"streamlit.elements.lib.column_types.ImageColumnConfig"},{".class":"NoneType"}]}]],"required_keys":[]}}},"ColumnType":{".class":"SymbolTableNode","kind":"Gdef","node":{".class":"TypeAlias","alias_tvars":[],"column":0,"fullname":"streamlit.elements.lib.column_types.ColumnType","line":28,"no_args":false,"normalized":false,"target":{".class":"UnionType","items":[{".class":"LiteralType","fallback":"builtins.str","value":"object"},{".class":"LiteralType","fallback":"builtins.str","value":"text"},{".class":"LiteralType","fallback":"builtins.str","value":"number"},{".class":"LiteralType","fallback":"builtins.str","value":"checkbox"},{".class":"LiteralType","fallback":"builtins.str","value":"selectbox"},{".class":"LiteralType","fallback":"builtins.str","value":"list"},{".class":"LiteralType","fallback":"builtins.str","value":"datetime"},{".class":"LiteralType","fallback":"builtins.str","value":"date"},{".class":"LiteralType","fallback":"builtins.str","value":"time"},{".class":"LiteralType","fallback":"builtins.str","value":"link"},{".class":"LiteralType","fallback":"builtins.str","value":"line_chart"},{".class":"LiteralType","fallback":"builtins.str","value":"bar_chart"},{".class":"LiteralType","fallback":"builtins.str","value":"area_chart"},{".class":"LiteralType","fallback":"builtins.str","value":"image"},{".class":"LiteralType","fallback":"builtins.str","value":"progress"}]}}},"ColumnWidth":{".class":"SymbolTableNode","kind":"Gdef","node":{".class":"TypeAlias","alias_tvars":[],"column":0,"fullname":"streamlit.elements.lib.column_types.ColumnWidth","line":24,"no_args":false,"normalized":false,"target":{".class":"UnionType","items":[{".class":"LiteralType","fallback":"builtins.str","value":"small"},{".class":"LiteralType","fallback":"builtins.str","value":"medium"},{".class":"LiteralType","fallback":"builtins.str","value":"large"}]}}},"DateColumn":{".class":"SymbolTableNode","kind":"Gdef","node":{".class":"Decorator","func":{".class":"FuncDef","abstract_status":0,"arg_kinds":[1,5,5,5,5,5,5,5,5,5],"arg_names":["label","width","help","disabled","required","default","format","min_value","max_value","step"],"dataclass_transform_spec":null,"flags":["is_decorated"],"fullname":"streamlit.elements.lib.column_types.DateColumn","name":"DateColumn","type":{".class":"CallableType","arg_kinds":[1,5,5,5,5,5,5,5,5,5],"arg_names":["label","width","help","disabled","required","default","format","min_value","max_value","step"],"arg_types":[{".class":"UnionType","items":["builtins.str",{".class":"NoneType"}]},{".class":"UnionType","items":[{".class":"TypeAliasType","args":[],"type_ref":"streamlit.elements.lib.column_types.ColumnWidth"},{".class":"NoneType"}]},{".class":"UnionType","items":["builtins.str",{".class":"NoneType"}]},{".class":"UnionType","items":["builtins.bool",{".class":"NoneType"}]},{".class":"UnionType","items":["builtins.bool",{".class":"NoneType"}]},{".class":"UnionType","items":["datetime.date",{".class":"NoneType"}]},{".class":"UnionType","items":["builtins.str",{".class":"NoneType"}]},{".class":"UnionType","items":["datetime.date",{".class":"NoneType"}]},{".class":"UnionType","items":["datetime.date",{".class":"NoneType"}]},{".class":"UnionType","items":["builtins.int",{".class":"NoneType"}]}],"bound_args":[],"def_extras":{"first_arg":null},"fallback":"builtins.function","from_concatenate":false,"implicit":false,"imprecise_arg_kinds":false,"is_ellipsis_args":false,"name":"DateColumn","ret_type":{".class":"TypeAliasType","args":[],"type_ref":"streamlit.elements.lib.column_types.ColumnConfig"},"type_guard":null,"type_is":null,"unpack_kwargs":false,"variables":[]}},"is_overload":false,"var":{".class":"Var","flags":["is_ready","is_inferred"],"fullname":"streamlit.elements.lib.column_types.DateColumn","name":"DateColumn","type":{".class":"CallableType","arg_kinds":[1,5,5,5,5,5,5,5,5,5],"arg_names":["label","width","help","disabled","required","default","format","min_value","max_value","step"],"arg_types":[{".class":"UnionType","items":["builtins.str",{".class":"NoneType"}]},{".class":"UnionType","items":[{".class":"TypeAliasType","args":[],"type_ref":"streamlit.elements.lib.column_types.ColumnWidth"},{".class":"NoneType"}]},{".class":"UnionType","items":["builtins.str",{".class":"NoneType"}]},{".class":"UnionType","items":["builtins.bool",{".class":"NoneType"}]},{".class":"UnionType","items":["builtins.bool",{".class":"NoneType"}]},{".class":"UnionType","items":["datetime.date",{".class":"NoneType"}]},{".class":"UnionType","items":["builtins.str",{".class":"NoneType"}]},{".class":"UnionType","items":["datetime.date",{".class":"NoneType"}]},{".class":"UnionType","items":["datetime.date",{".class":"NoneType"}]},{".class":"UnionType","items":["builtins.int",{".class":"NoneType"}]}],"bound_args":[],"def_extras":{"first_arg":null},"fallback":"builtins.function","from_concatenate":false,"implicit":false,"imprecise_arg_kinds":false,"is_ellipsis_args":false,"name":"DateColumn","ret_type":{".class":"TypeAliasType","args":[],"type_ref":"streamlit.elements.lib.column_types.ColumnConfig"},"type_guard":null,"type_is":null,"unpack_kwargs":false,"variables":[]}}}},"DateColumnConfig":{".class":"SymbolTableNode","kind":"Gdef","node":{".class":"TypeInfo","_promote":[],"abstract_attributes":[],"alt_promote":null,"bases":["typing._TypedDict"],"dataclass_transform_spec":null,"declared_metaclass":null,"defn":{".class":"ClassDef","fullname":"streamlit.elements.lib.column_types.DateColumnConfig","name":"DateColumnConfig","type_vars":[]},"deletable_attributes":[],"flags":[],"fullname":"streamlit.elements.lib.column_types.DateColumnConfig","has_param_spec_type":false,"metaclass_type":null,"metadata":{},"module_name":"streamlit.elements.lib.column_types","mro":["streamlit.elements.lib.column_types.DateColumnConfig","typing._TypedDict","typing.Mapping","typing.Collection","typing.Iterable","typing.Container","builtins.object"],"names":{".class":"SymbolTable"},"self_type":null,"slots":null,"tuple_type":null,"type_vars":[],"typeddict_type":{".class":"TypedDictType","fallback":"typing._TypedDict","items":[["type",{".class":"LiteralType","fallback":"builtins.str","value":"date"}],["format",{".class":"UnionType","items":["builtins.str",{".class":"NoneType"}]}],["min_value",{".class":"UnionType","items":["builtins.str",{".class":"NoneType"}]}],["max_value",{".class":"UnionType","items":["builtins.str",{".class":"NoneType"}]}],["step",{".class":"UnionType","items":["builtins.int",{".class":"NoneType"}]}]],"required_keys":["type"]}}},"DatetimeColumn":{".class":"SymbolTableNode","kind":"Gdef","node":{".class":"Decorator","func":{".class":"FuncDef","abstract_status":0,"arg_kinds":[1,5,5,5,5,5,5,5,5,5,5],"arg_names":["label","width","help","disabled","required","default","format","min_value","max_value","step","timezone"],"dataclass_transform_spec":null,"flags":["is_decorated"],"fullname":"streamlit.elements.lib.column_types.DatetimeColumn","name":"DatetimeColumn","type":{".class":"CallableType","arg_kinds":[1,5,5,5,5,5,5,5,5,5,5],"arg_names":["label","width","help","disabled","required","default","format","min_value","max_value","step","timezone"],"arg_types":[{".class":"UnionType","items":["builtins.str",{".class":"NoneType"}]},{".class":"UnionType","items":[{".class":"TypeAliasType","args":[],"type_ref":"streamlit.elements.lib.column_types.ColumnWidth"},{".class":"NoneType"}]},{".class":"UnionType","items":["builtins.str",{".class":"NoneType"}]},{".class":"UnionType","items":["builtins.bool",{".class":"NoneType"}]},{".class":"UnionType","items":["builtins.bool",{".class":"NoneType"}]},{".class":"UnionType","items":["datetime.datetime",{".class":"NoneType"}]},{".class":"UnionType","items":["builtins.str",{".class":"NoneType"}]},{".class":"UnionType","items":["datetime.datetime",{".class":"NoneType"}]},{".class":"UnionType","items":["datetime.datetime",{".class":"NoneType"}]},{".class":"UnionType","items":["builtins.int","builtins.float","datetime.timedelta",{".class":"NoneType"}]},{".class":"UnionType","items":["builtins.str",{".class":"NoneType"}]}],"bound_args":[],"def_extras":{"first_arg":null},"fallback":"builtins.function","from_concatenate":false,"implicit":false,"imprecise_arg_kinds":false,"is_ellipsis_args":false,"name":"DatetimeColumn","ret_type":{".class":"TypeAliasType","args":[],"type_ref":"streamlit.elements.lib.column_types.ColumnConfig"},"type_guard":null,"type_is":null,"unpack_kwargs":false,"variables":[]}},"is_overload":false,"var":{".class":"Var","flags":["is_ready","is_inferred"],"fullname":"streamlit.elements.lib.column_types.DatetimeColumn","name":"DatetimeColumn","type":{".class":"CallableType","arg_kinds":[1,5,5,5,5,5,5,5,5,5,5],"arg_names":["label","width","help","disabled","required","default","format","min_value","max_value","step","timezone"],"arg_types":[{".class":"UnionType","items":["builtins.str",{".class":"NoneType"}]},{".class":"UnionType","items":[{".class":"TypeAliasType","args":[],"type_ref":"streamlit.elements.lib.column_types.ColumnWidth"},{".class":"NoneType"}]},{".class":"UnionType","items":["builtins.str",{".class":"NoneType"}]},{".class":"UnionType","items":["builtins.bool",{".class":"NoneType"}]},{".class":"UnionType","items":["builtins.bool",{".class":"NoneType"}]},{".class":"UnionType","items":["datetime.datetime",{".class":"NoneType"}]},{".class":"UnionType","items":["builtins.str",{".class":"NoneType"}]},{".class":"UnionType","items":["datetime.datetime",{".class":"NoneType"}]},{".class":"UnionType","items":["datetime.datetime",{".class":"NoneType"}]},{".class":"UnionType","items":["builtins.int","builtins.float","datetime.timedelta",{".class":"NoneType"}]},{".class":"UnionType","items":["builtins.str",{".class":"NoneType"}]}],"bound_args":[],"def_extras":{"first_arg":null},"fallback":"builtins.function","from_concatenate":false,"implicit":false,"imprecise_arg_kinds":false,"is_ellipsis_args":false,"name":"DatetimeColumn","ret_type":{".class":"TypeAliasType","args":[],"type_ref":"streamlit.elements.lib.column_types.ColumnConfig"},"type_guard":null,"type_is":null,"unpack_kwargs":false,"variables":[]}}}},"DatetimeColumnConfig":{".class":"SymbolTableNode","kind":"Gdef","node":{".class":"TypeInfo","_promote":[],"abstract_attributes":[],"alt_promote":null,"bases":["typing._TypedDict"],"dataclass_transform_spec":null,"declared_metaclass":null,"defn":{".class":"ClassDef","fullname":"streamlit.elements.lib.column_types.DatetimeColumnConfig","name":"DatetimeColumnConfig","type_vars":[]},"deletable_attributes":[],"flags":[],"fullname":"streamlit.elements.lib.column_types.DatetimeColumnConfig","has_param_spec_type":false,"metaclass_type":null,"metadata":{},"module_name":"streamlit.elements.lib.column_types","mro":["streamlit.elements.lib.column_types.DatetimeColumnConfig","typing._TypedDict","typing.Mapping","typing.Collection","typing.Iterable","typing.Container","builtins.object"],"names":{".class":"SymbolTable"},"self_type":null,"slots":null,"tuple_type":null,"type_vars":[],"typeddict_type":{".class":"TypedDictType","fallback":"typing._TypedDict","items":[["type",{".class":"LiteralType","fallback":"builtins.str","value":"datetime"}],["format",{".class":"UnionType","items":["builtins.str",{".class":"NoneType"}]}],["min_value",{".class":"UnionType","items":["builtins.str",{".class":"NoneType"}]}],["max_value",{".class":"UnionType","items":["builtins.str",{".class":"NoneType"}]}],["step",{".class":"UnionType","items":["builtins.int","builtins.float",{".class":"NoneType"}]}],["timezone",{".class":"UnionType","items":["builtins.str",{".class":"NoneType"}]}]],"required_keys":["type"]}}},"ImageColumn":{".class":"SymbolTableNode","kind":"Gdef","node":{".class":"Decorator","func":{".class":"FuncDef","abstract_status":0,"arg_kinds":[1,5,5],"arg_names":["label","width","help"],"dataclass_transform_spec":null,"flags":["is_decorated"],"fullname":"streamlit.elements.lib.column_types.ImageColumn","name":"ImageColumn","type":{".class":"CallableType","arg_kinds":[1,5,5],"arg_names":["label","width","help"],"arg_types":[{".class":"UnionType","items":["builtins.str",{".class":"NoneType"}]},{".class":"UnionType","items":[{".class":"TypeAliasType","args":[],"type_ref":"streamlit.elements.lib.column_types.ColumnWidth"},{".class":"NoneType"}]},{".class":"UnionType","items":["builtins.str",{".class":"NoneType"}]}],"bound_args":[],"def_extras":{"first_arg":null},"fallback":"builtins.function","from_concatenate":false,"implicit":false,"imprecise_arg_kinds":false,"is_ellipsis_args":false,"name":"ImageColumn","ret_type":{".class":"AnyType","missing_import_name":null,"source_any":null,"type_of_any":1},"type_guard":null,"type_is":null,"unpack_kwargs":false,"variables":[]}},"is_overload":false,"var":{".class":"Var","flags":["is_ready","is_inferred"],"fullname":"streamlit.elements.lib.column_types.ImageColumn","name":"ImageColumn","type":{".class":"CallableType","arg_kinds":[1,5,5],"arg_names":["label","width","help"],"arg_types":[{".class":"UnionType","items":["builtins.str",{".class":"NoneType"}]},{".class":"UnionType","items":[{".class":"TypeAliasType","args":[],"type_ref":"streamlit.elements.lib.column_types.ColumnWidth"},{".class":"NoneType"}]},{".class":"UnionType","items":["builtins.str",{".class":"NoneType"}]}],"bound_args":[],"def_extras":{"first_arg":null},"fallback":"builtins.function","from_concatenate":false,"implicit":false,"imprecise_arg_kinds":false,"is_ellipsis_args":false,"name":"ImageColumn","ret_type":{".class":"AnyType","missing_import_name":null,"source_any":null,"type_of_any":1},"type_guard":null,"type_is":null,"unpack_kwargs":false,"variables":[]}}}},"ImageColumnConfig":{".class":"SymbolTableNode","kind":"Gdef","node":{".class":"TypeInfo","_promote":[],"abstract_attributes":[],"alt_promote":null,"bases":["typing._TypedDict"],"dataclass_transform_spec":null,"declared_metaclass":null,"defn":{".class":"ClassDef","fullname":"streamlit.elements.lib.column_types.ImageColumnConfig","name":"ImageColumnConfig","type_vars":[]},"deletable_attributes":[],"flags":[],"fullname":"streamlit.elements.lib.column_types.ImageColumnConfig","has_param_spec_type":false,"metaclass_type":null,"metadata":{},"module_name":"streamlit.elements.lib.column_types","mro":["streamlit.elements.lib.column_types.ImageColumnConfig","typing._TypedDict","typing.Mapping","typing.Collection","typing.Iterable","typing.Container","builtins.object"],"names":{".class":"SymbolTable"},"self_type":null,"slots":null,"tuple_type":null,"type_vars":[],"typeddict_type":{".class":"TypedDictType","fallback":"typing._TypedDict","items":[["type",{".class":"LiteralType","fallback":"builtins.str","value":"image"}]],"required_keys":["type"]}}},"Iterable":{".class":"SymbolTableNode","cross_ref":"typing.Iterable","kind":"Gdef"},"LineChartColumn":{".class":"SymbolTableNode","kind":"Gdef","node":{".class":"Decorator","func":{".class":"FuncDef","abstract_status":0,"arg_kinds":[1,5,5,5,5],"arg_names":["label","width","help","y_min","y_max"],"dataclass_transform_spec":null,"flags":["is_decorated"],"fullname":"streamlit.elements.lib.column_types.LineChartColumn","name":"LineChartColumn","type":{".class":"CallableType","arg_kinds":[1,5,5,5,5],"arg_names":["label","width","help","y_min","y_max"],"arg_types":[{".class":"UnionType","items":["builtins.str",{".class":"NoneType"}]},{".class":"UnionType","items":[{".class":"TypeAliasType","args":[],"type_ref":"streamlit.elements.lib.column_types.ColumnWidth"},{".class":"NoneType"}]},{".class":"UnionType","items":["builtins.str",{".class":"NoneType"}]},{".class":"UnionType","items":["builtins.int","builtins.float",{".class":"NoneType"}]},{".class":"UnionType","items":["builtins.int","builtins.float",{".class":"NoneType"}]}],"bound_args":[],"def_extras":{"first_arg":null},"fallback":"builtins.function","from_concatenate":false,"implicit":false,"imprecise_arg_kinds":false,"is_ellipsis_args":false,"name":"LineChartColumn","ret_type":{".class":"TypeAliasType","args":[],"type_ref":"streamlit.elements.lib.column_types.ColumnConfig"},"type_guard":null,"type_is":null,"unpack_kwargs":false,"variables":[]}},"is_overload":false,"var":{".class":"Var","flags":["is_ready","is_inferred"],"fullname":"streamlit.elements.lib.column_types.LineChartColumn","name":"LineChartColumn","type":{".class":"CallableType","arg_kinds":[1,5,5,5,5],"arg_names":["label","width","help","y_min","y_max"],"arg_types":[{".class":"UnionType","items":["builtins.str",{".class":"NoneType"}]},{".class":"UnionType","items":[{".class":"TypeAliasType","args":[],"type_ref":"streamlit.elements.lib.column_types.ColumnWidth"},{".class":"NoneType"}]},{".class":"UnionType","items":["builtins.str",{".class":"NoneType"}]},{".class":"UnionType","items":["builtins.int","builtins.float",{".class":"NoneType"}]},{".class":"UnionType","items":["builtins.int","builtins.float",{".class":"NoneType"}]}],"bound_args":[],"def_extras":{"first_arg":null},"fallback":"builtins.function","from_concatenate":false,"implicit":false,"imprecise_arg_kinds":false,"is_ellipsis_args":false,"name":"LineChartColumn","ret_type":{".class":"TypeAliasType","args":[],"type_ref":"streamlit.elements.lib.column_types.ColumnConfig"},"type_guard":null,"type_is":null,"unpack_kwargs":false,"variables":[]}}}},"LineChartColumnConfig":{".class":"SymbolTableNode","kind":"Gdef","node":{".class":"TypeInfo","_promote":[],"abstract_attributes":[],"alt_promote":null,"bases":["typing._TypedDict"],"dataclass_transform_spec":null,"declared_metaclass":null,"defn":{".class":"ClassDef","fullname":"streamlit.elements.lib.column_types.LineChartColumnConfig","name":"LineChartColumnConfig","type_vars":[]},"deletable_attributes":[],"flags":[],"fullname":"streamlit.elements.lib.column_types.LineChartColumnConfig","has_param_spec_type":false,"metaclass_type":null,"metadata":{},"module_name":"streamlit.elements.lib.column_types","mro":["streamlit.elements.lib.column_types.LineChartColumnConfig","typing._TypedDict","typing.Mapping","typing.Collection","typing.Iterable","typing.Container","builtins.object"],"names":{".class":"SymbolTable"},"self_type":null,"slots":null,"tuple_type":null,"type_vars":[],"typeddict_type":{".class":"TypedDictType","fallback":"typing._TypedDict","items":[["type",{".class":"LiteralType","fallback":"builtins.str","value":"line_chart"}],["y_min",{".class":"UnionType","items":["builtins.int","builtins.float",{".class":"NoneType"}]}],["y_max",{".class":"UnionType","items":["builtins.int","builtins.float",{".class":"NoneType"}]}]],"required_keys":["type"]}}},"LinkColumn":{".class":"SymbolTableNode","kind":"Gdef","node":{".class":"Decorator","func":{".class":"FuncDef","abstract_status":0,"arg_kinds":[1,5,5,5,5,5,5,5,5],"arg_names":["label","width","help","disabled","required","default","max_chars","validate","display_text"],"dataclass_transform_spec":null,"flags":["is_decorated"],"fullname":"streamlit.elements.lib.column_types.LinkColumn","name":"LinkColumn","type":{".class":"CallableType","arg_kinds":[1,5,5,5,5,5,5,5,5],"arg_names":["label","width","help","disabled","required","default","max_chars","validate","display_text"],"arg_types":[{".class":"UnionType","items":["builtins.str",{".class":"NoneType"}]},{".class":"UnionType","items":[{".class":"TypeAliasType","args":[],"type_ref":"streamlit.elements.lib.column_types.ColumnWidth"},{".class":"NoneType"}]},{".class":"UnionType","items":["builtins.str",{".class":"NoneType"}]},{".class":"UnionType","items":["builtins.bool",{".class":"NoneType"}]},{".class":"UnionType","items":["builtins.bool",{".class":"NoneType"}]},{".class":"UnionType","items":["builtins.str",{".class":"NoneType"}]},{".class":"UnionType","items":["builtins.int",{".class":"NoneType"}]},{".class":"UnionType","items":["builtins.str",{".class":"NoneType"}]},{".class":"UnionType","items":["builtins.str",{".class":"NoneType"}]}],"bound_args":[],"def_extras":{"first_arg":null},"fallback":"builtins.function","from_concatenate":false,"implicit":false,"imprecise_arg_kinds":false,"is_ellipsis_args":false,"name":"LinkColumn","ret_type":{".class":"TypeAliasType","args":[],"type_ref":"streamlit.elements.lib.column_types.ColumnConfig"},"type_guard":null,"type_is":null,"unpack_kwargs":false,"variables":[]}},"is_overload":false,"var":{".class":"Var","flags":["is_ready","is_inferred"],"fullname":"streamlit.elements.lib.column_types.LinkColumn","name":"LinkColumn","type":{".class":"CallableType","arg_kinds":[1,5,5,5,5,5,5,5,5],"arg_names":["label","width","help","disabled","required","default","max_chars","validate","display_text"],"arg_types":[{".class":"UnionType","items":["builtins.str",{".class":"NoneType"}]},{".class":"UnionType","items":[{".class":"TypeAliasType","args":[],"type_ref":"streamlit.elements.lib.column_types.ColumnWidth"},{".class":"NoneType"}]},{".class":"UnionType","items":["builtins.str",{".class":"NoneType"}]},{".class":"UnionType","items":["builtins.bool",{".class":"NoneType"}]},{".class":"UnionType","items":["builtins.bool",{".class":"NoneType"}]},{".class":"UnionType","items":["builtins.str",{".class":"NoneType"}]},{".class":"UnionType","items":["builtins.int",{".class":"NoneType"}]},{".class":"UnionType","items":["builtins.str",{".class":"NoneType"}]},{".class":"UnionType","items":["builtins.str",{".class":"NoneType"}]}],"bound_args":[],"def_extras":{"first_arg":null},"fallback":"builtins.function","from_concatenate":false,"implicit":false,"imprecise_arg_kinds":false,"is_ellipsis_args":false,"name":"LinkColumn","ret_type":{".class":"TypeAliasType","args":[],"type_ref":"streamlit.elements.lib.column_types.ColumnConfig"},"type_guard":null,"type_is":null,"unpack_kwargs":false,"variables":[]}}}},"LinkColumnConfig":{".class":"SymbolTableNode","kind":"Gdef","node":{".class":"TypeInfo","_promote":[],"abstract_attributes":[],"alt_promote":null,"bases":["typing._TypedDict"],"dataclass_transform_spec":null,"declared_metaclass":null,"defn":{".class":"ClassDef","fullname":"streamlit.elements.lib.column_types.LinkColumnConfig","name":"LinkColumnConfig","type_vars":[]},"deletable_attributes":[],"flags":[],"fullname":"streamlit.elements.lib.column_types.LinkColumnConfig","has_param_spec_type":false,"metaclass_type":null,"metadata":{},"module_name":"streamlit.elements.lib.column_types","mro":["streamlit.elements.lib.column_types.LinkColumnConfig","typing._TypedDict","typing.Mapping","typing.Collection","typing.Iterable","typing.Container","builtins.object"],"names":{".class":"SymbolTable"},"self_type":null,"slots":null,"tuple_type":null,"type_vars":[],"typeddict_type":{".class":"TypedDictType","fallback":"typing._TypedDict","items":[["type",{".class":"LiteralType","fallback":"builtins.str","value":"link"}],["max_chars",{".class":"UnionType","items":["builtins.int",{".class":"NoneType"}]}],["validate",{".class":"UnionType","items":["builtins.str",{".class":"NoneType"}]}],["display_text",{".class":"UnionType","items":["builtins.str",{".class":"NoneType"}]}]],"required_keys":["type"]}}},"ListColumn":{".class":"SymbolTableNode","kind":"Gdef","node":{".class":"Decorator","func":{".class":"FuncDef","abstract_status":0,"arg_kinds":[1,5,5],"arg_names":["label","width","help"],"dataclass_transform_spec":null,"flags":["is_decorated"],"fullname":"streamlit.elements.lib.column_types.ListColumn","name":"ListColumn","type":{".class":"CallableType","arg_kinds":[1,5,5],"arg_names":["label","width","help"],"arg_types":[{".class":"UnionType","items":["builtins.str",{".class":"NoneType"}]},{".class":"UnionType","items":[{".class":"TypeAliasType","args":[],"type_ref":"streamlit.elements.lib.column_types.ColumnWidth"},{".class":"NoneType"}]},{".class":"UnionType","items":["builtins.str",{".class":"NoneType"}]}],"bound_args":[],"def_extras":{"first_arg":null},"fallback":"builtins.function","from_concatenate":false,"implicit":false,"imprecise_arg_kinds":false,"is_ellipsis_args":false,"name":"ListColumn","ret_type":{".class":"AnyType","missing_import_name":null,"source_any":null,"type_of_any":1},"type_guard":null,"type_is":null,"unpack_kwargs":false,"variables":[]}},"is_overload":false,"var":{".class":"Var","flags":["is_ready","is_inferred"],"fullname":"streamlit.elements.lib.column_types.ListColumn","name":"ListColumn","type":{".class":"CallableType","arg_kinds":[1,5,5],"arg_names":["label","width","help"],"arg_types":[{".class":"UnionType","items":["builtins.str",{".class":"NoneType"}]},{".class":"UnionType","items":[{".class":"TypeAliasType","args":[],"type_ref":"streamlit.elements.lib.column_types.ColumnWidth"},{".class":"NoneType"}]},{".class":"UnionType","items":["builtins.str",{".class":"NoneType"}]}],"bound_args":[],"def_extras":{"first_arg":null},"fallback":"builtins.function","from_concatenate":false,"implicit":false,"imprecise_arg_kinds":false,"is_ellipsis_args":false,"name":"ListColumn","ret_type":{".class":"AnyType","missing_import_name":null,"source_any":null,"type_of_any":1},"type_guard":null,"type_is":null,"unpack_kwargs":false,"variables":[]}}}},"ListColumnConfig":{".class":"SymbolTableNode","kind":"Gdef","node":{".class":"TypeInfo","_promote":[],"abstract_attributes":[],"alt_promote":null,"bases":["typing._TypedDict"],"dataclass_transform_spec":null,"declared_metaclass":null,"defn":{".class":"ClassDef","fullname":"streamlit.elements.lib.column_types.ListColumnConfig","name":"ListColumnConfig","type_vars":[]},"deletable_attributes":[],"flags":[],"fullname":"streamlit.elements.lib.column_types.ListColumnConfig","has_param_spec_type":false,"metaclass_type":null,"metadata":{},"module_name":"streamlit.elements.lib.column_types","mro":["streamlit.elements.lib.column_types.ListColumnConfig","typing._TypedDict","typing.Mapping","typing.Collection","typing.Iterable","typing.Container","builtins.object"],"names":{".class":"SymbolTable"},"self_type":null,"slots":null,"tuple_type":null,"type_vars":[],"typeddict_type":{".class":"TypedDictType","fallback":"typing._TypedDict","items":[["type",{".class":"LiteralType","fallback":"builtins.str","value":"list"}]],"required_keys":["type"]}}},"Literal":{".class":"SymbolTableNode","cross_ref":"typing.Literal","kind":"Gdef"},"NotRequired":{".class":"SymbolTableNode","cross_ref":"typing.NotRequired","kind":"Gdef"},"NumberColumn":{".class":"SymbolTableNode","kind":"Gdef","node":{".class":"Decorator","func":{".class":"FuncDef","abstract_status":0,"arg_kinds":[1,5,5,5,5,5,5,5,5,5],"arg_names":["label","width","help","disabled","required","default","format","min_value","max_value","step"],"dataclass_transform_spec":null,"flags":["is_decorated"],"fullname":"streamlit.elements.lib.column_types.NumberColumn","name":"NumberColumn","type":{".class":"CallableType","arg_kinds":[1,5,5,5,5,5,5,5,5,5],"arg_names":["label","width","help","disabled","required","default","format","min_value","max_value","step"],"arg_types":[{".class":"UnionType","items":["builtins.str",{".class":"NoneType"}]},{".class":"UnionType","items":[{".class":"TypeAliasType","args":[],"type_ref":"streamlit.elements.lib.column_types.ColumnWidth"},{".class":"NoneType"}]},{".class":"UnionType","items":["builtins.str",{".class":"NoneType"}]},{".class":"UnionType","items":["builtins.bool",{".class":"NoneType"}]},{".class":"UnionType","items":["builtins.bool",{".class":"NoneType"}]},{".class":"UnionType","items":["builtins.int","builtins.float",{".class":"NoneType"}]},{".class":"UnionType","items":["builtins.str",{".class":"NoneType"}]},{".class":"UnionType","items":["builtins.int","builtins.float",{".class":"NoneType"}]},{".class":"UnionType","items":["builtins.int","builtins.float",{".class":"NoneType"}]},{".class":"UnionType","items":["builtins.int","builtins.float",{".class":"NoneType"}]}],"bound_args":[],"def_extras":{"first_arg":null},"fallback":"builtins.function","from_concatenate":false,"implicit":false,"imprecise_arg_kinds":false,"is_ellipsis_args":false,"name":"NumberColumn","ret_type":{".class":"TypeAliasType","args":[],"type_ref":"streamlit.elements.lib.column_types.ColumnConfig"},"type_guard":null,"type_is":null,"unpack_kwargs":false,"variables":[]}},"is_overload":false,"var":{".class":"Var","flags":["is_ready","is_inferred"],"fullname":"streamlit.elements.lib.column_types.NumberColumn","name":"NumberColumn","type":{".class":"CallableType","arg_kinds":[1,5,5,5,5,5,5,5,5,5],"arg_names":["label","width","help","disabled","required","default","format","min_value","max_value","step"],"arg_types":[{".class":"UnionType","items":["builtins.str",{".class":"NoneType"}]},{".class":"UnionType","items":[{".class":"TypeAliasType","args":[],"type_ref":"streamlit.elements.lib.column_types.ColumnWidth"},{".class":"NoneType"}]},{".class":"UnionType","items":["builtins.str",{".class":"NoneType"}]},{".class":"UnionType","items":["builtins.bool",{".class":"NoneType"}]},{".class":"UnionType","items":["builtins.bool",{".class":"NoneType"}]},{".class":"UnionType","items":["builtins.int","builtins.float",{".class":"NoneType"}]},{".class":"UnionType","items":["builtins.str",{".class":"NoneType"}]},{".class":"UnionType","items":["builtins.int","builtins.float",{".class":"NoneType"}]},{".class":"UnionType","items":["builtins.int","builtins.float",{".class":"NoneType"}]},{".class":"UnionType","items":["builtins.int","builtins.float",{".class":"NoneType"}]}],"bound_args":[],"def_extras":{"first_arg":null},"fallback":"builtins.function","from_concatenate":false,"implicit":false,"imprecise_arg_kinds":false,"is_ellipsis_args":false,"name":"NumberColumn","ret_type":{".class":"TypeAliasType","args":[],"type_ref":"streamlit.elements.lib.column_types.ColumnConfig"},"type_guard":null,"type_is":null,"unpack_kwargs":false,"variables":[]}}}},"NumberColumnConfig":{".class":"SymbolTableNode","kind":"Gdef","node":{".class":"TypeInfo","_promote":[],"abstract_attributes":[],"alt_promote":null,"bases":["typing._TypedDict"],"dataclass_transform_spec":null,"declared_metaclass":null,"defn":{".class":"ClassDef","fullname":"streamlit.elements.lib.column_types.NumberColumnConfig","name":"NumberColumnConfig","type_vars":[]},"deletable_attributes":[],"flags":[],"fullname":"streamlit.elements.lib.column_types.NumberColumnConfig","has_param_spec_type":false,"metaclass_type":null,"metadata":{},"module_name":"streamlit.elements.lib.column_types","mro":["streamlit.elements.lib.column_types.NumberColumnConfig","typing._TypedDict","typing.Mapping","typing.Collection","typing.Iterable","typing.Container","builtins.object"],"names":{".class":"SymbolTable"},"self_type":null,"slots":null,"tuple_type":null,"type_vars":[],"typeddict_type":{".class":"TypedDictType","fallback":"typing._TypedDict","items":[["type",{".class":"LiteralType","fallback":"builtins.str","value":"number"}],["format",{".class":"UnionType","items":["builtins.str",{".class":"NoneType"}]}],["min_value",{".class":"UnionType","items":["builtins.int","builtins.float",{".class":"NoneType"}]}],["max_value",{".class":"UnionType","items":["builtins.int","builtins.float",{".class":"NoneType"}]}],["step",{".class":"UnionType","items":["builtins.int","builtins.float",{".class":"NoneType"}]}]],"required_keys":["type"]}}},"ProgressColumn":{".class":"SymbolTableNode","kind":"Gdef","node":{".class":"Decorator","func":{".class":"FuncDef","abstract_status":0,"arg_kinds":[1,5,5,5,5,5],"arg_names":["label","width","help","format","min_value","max_value"],"dataclass_transform_spec":null,"flags":["is_decorated"],"fullname":"streamlit.elements.lib.column_types.ProgressColumn","name":"ProgressColumn","type":{".class":"CallableType","arg_kinds":[1,5,5,5,5,5],"arg_names":["label","width","help","format","min_value","max_value"],"arg_types":[{".class":"UnionType","items":["builtins.str",{".class":"NoneType"}]},{".class":"UnionType","items":[{".class":"TypeAliasType","args":[],"type_ref":"streamlit.elements.lib.column_types.ColumnWidth"},{".class":"NoneType"}]},{".class":"UnionType","items":["builtins.str",{".class":"NoneType"}]},{".class":"UnionType","items":["builtins.str",{".class":"NoneType"}]},{".class":"UnionType","items":["builtins.int","builtins.float",{".class":"NoneType"}]},{".class":"UnionType","items":["builtins.int","builtins.float",{".class":"NoneType"}]}],"bound_args":[],"def_extras":{"first_arg":null},"fallback":"builtins.function","from_concatenate":false,"implicit":false,"imprecise_arg_kinds":false,"is_ellipsis_args":false,"name":"ProgressColumn","ret_type":{".class":"TypeAliasType","args":[],"type_ref":"streamlit.elements.lib.column_types.ColumnConfig"},"type_guard":null,"type_is":null,"unpack_kwargs":false,"variables":[]}},"is_overload":false,"var":{".class":"Var","flags":["is_ready","is_inferred"],"fullname":"streamlit.elements.lib.column_types.ProgressColumn","name":"ProgressColumn","type":{".class":"CallableType","arg_kinds":[1,5,5,5,5,5],"arg_names":["label","width","help","format","min_value","max_value"],"arg_types":[{".class":"UnionType","items":["builtins.str",{".class":"NoneType"}]},{".class":"UnionType","items":[{".class":"TypeAliasType","args":[],"type_ref":"streamlit.elements.lib.column_types.ColumnWidth"},{".class":"NoneType"}]},{".class":"UnionType","items":["builtins.str",{".class":"NoneType"}]},{".class":"UnionType","items":["builtins.str",{".class":"NoneType"}]},{".class":"UnionType","items":["builtins.int","builtins.float",{".class":"NoneType"}]},{".class":"UnionType","items":["builtins.int","builtins.float",{".class":"NoneType"}]}],"bound_args":[],"def_extras":{"first_arg":null},"fallback":"builtins.function","from_concatenate":false,"implicit":false,"imprecise_arg_kinds":false,"is_ellipsis_args":false,"name":"ProgressColumn","ret_type":{".class":"TypeAliasType","args":[],"type_ref":"streamlit.elements.lib.column_types.ColumnConfig"},"type_guard":null,"type_is":null,"unpack_kwargs":false,"variables":[]}}}},"ProgressColumnConfig":{".class":"SymbolTableNode","kind":"Gdef","node":{".class":"TypeInfo","_promote":[],"abstract_attributes":[],"alt_promote":null,"bases":["typing._TypedDict"],"dataclass_transform_spec":null,"declared_metaclass":null,"defn":{".class":"ClassDef","fullname":"streamlit.elements.lib.column_types.ProgressColumnConfig","name":"ProgressColumnConfig","type_vars":[]},"deletable_attributes":[],"flags":[],"fullname":"streamlit.elements.lib.column_types.ProgressColumnConfig","has_param_spec_type":false,"metaclass_type":null,"metadata":{},"module_name":"streamlit.elements.lib.column_types","mro":["streamlit.elements.lib.column_types.ProgressColumnConfig","typing._TypedDict","typing.Mapping","typing.Collection","typing.Iterable","typing.Container","builtins.object"],"names":{".class":"SymbolTable"},"self_type":null,"slots":null,"tuple_type":null,"type_vars":[],"typeddict_type":{".class":"TypedDictType","fallback":"typing._TypedDict","items":[["type",{".class":"LiteralType","fallback":"builtins.str","value":"progress"}],["format",{".class":"UnionType","items":["builtins.str",{".class":"NoneType"}]}],["min_value",{".class":"UnionType","items":["builtins.int","builtins.float",{".class":"NoneType"}]}],["max_value",{".class":"UnionType","items":["builtins.int","builtins.float",{".class":"NoneType"}]}]],"required_keys":["type"]}}},"SelectboxColumn":{".class":"SymbolTableNode","kind":"Gdef","node":{".class":"Decorator","func":{".class":"FuncDef","abstract_status":0,"arg_kinds":[1,5,5,5,5,5,5],"arg_names":["label","width","help","disabled","required","default","options"],"dataclass_transform_spec":null,"flags":["is_decorated"],"fullname":"streamlit.elements.lib.column_types.SelectboxColumn","name":"SelectboxColumn","type":{".class":"CallableType","arg_kinds":[1,5,5,5,5,5,5],"arg_names":["label","width","help","disabled","required","default","options"],"arg_types":[{".class":"UnionType","items":["builtins.str",{".class":"NoneType"}]},{".class":"UnionType","items":[{".class":"TypeAliasType","args":[],"type_ref":"streamlit.elements.lib.column_types.ColumnWidth"},{".class":"NoneType"}]},{".class":"UnionType","items":["builtins.str",{".class":"NoneType"}]},{".class":"UnionType","items":["builtins.bool",{".class":"NoneType"}]},{".class":"UnionType","items":["builtins.bool",{".class":"NoneType"}]},{".class":"UnionType","items":["builtins.str","builtins.int","builtins.float",{".class":"NoneType"}]},{".class":"UnionType","items":[{".class":"Instance","args":[{".class":"UnionType","items":["builtins.str","builtins.int","builtins.float"]}],"type_ref":"typing.Iterable"},{".class":"NoneType"}]}],"bound_args":[],"def_extras":{"first_arg":null},"fallback":"builtins.function","from_concatenate":false,"implicit":false,"imprecise_arg_kinds":false,"is_ellipsis_args":false,"name":"SelectboxColumn","ret_type":{".class":"TypeAliasType","args":[],"type_ref":"streamlit.elements.lib.column_types.ColumnConfig"},"type_guard":null,"type_is":null,"unpack_kwargs":false,"variables":[]}},"is_overload":false,"var":{".class":"Var","flags":["is_ready","is_inferred"],"fullname":"streamlit.elements.lib.column_types.SelectboxColumn","name":"SelectboxColumn","type":{".class":"CallableType","arg_kinds":[1,5,5,5,5,5,5],"arg_names":["label","width","help","disabled","required","default","options"],"arg_types":[{".class":"UnionType","items":["builtins.str",{".class":"NoneType"}]},{".class":"UnionType","items":[{".class":"TypeAliasType","args":[],"type_ref":"streamlit.elements.lib.column_types.ColumnWidth"},{".class":"NoneType"}]},{".class":"UnionType","items":["builtins.str",{".class":"NoneType"}]},{".class":"UnionType","items":["builtins.bool",{".class":"NoneType"}]},{".class":"UnionType","items":["builtins.bool",{".class":"NoneType"}]},{".class":"UnionType","items":["builtins.str","builtins.int","builtins.float",{".class":"NoneType"}]},{".class":"UnionType","items":[{".class":"Instance","args":[{".class":"UnionType","items":["builtins.str","builtins.int","builtins.float"]}],"type_ref":"typing.Iterable"},{".class":"NoneType"}]}],"bound_args":[],"def_extras":{"first_arg":null},"fallback":"builtins.function","from_concatenate":false,"implicit":false,"imprecise_arg_kinds":false,"is_ellipsis_args":false,"name":"SelectboxColumn","ret_type":{".class":"TypeAliasType","args":[],"type_ref":"streamlit.elements.lib.column_types.ColumnConfig"},"type_guard":null,"type_is":null,"unpack_kwargs":false,"variables":[]}}}},"SelectboxColumnConfig":{".class":"SymbolTableNode","kind":"Gdef","node":{".class":"TypeInfo","_promote":[],"abstract_attributes":[],"alt_promote":null,"bases":["typing._TypedDict"],"dataclass_transform_spec":null,"declared_metaclass":null,"defn":{".class":"ClassDef","fullname":"streamlit.elements.lib.column_types.SelectboxColumnConfig","name":"SelectboxColumnConfig","type_vars":[]},"deletable_attributes":[],"flags":[],"fullname":"streamlit.elements.lib.column_types.SelectboxColumnConfig","has_param_spec_type":false,"metaclass_type":null,"metadata":{},"module_name":"streamlit.elements.lib.column_types","mro":["streamlit.elements.lib.column_types.SelectboxColumnConfig","typing._TypedDict","typing.Mapping","typing.Collection","typing.Iterable","typing.Container","builtins.object"],"names":{".class":"SymbolTable"},"self_type":null,"slots":null,"tuple_type":null,"type_vars":[],"typeddict_type":{".class":"TypedDictType","fallback":"typing._TypedDict","items":[["type",{".class":"LiteralType","fallback":"builtins.str","value":"selectbox"}],["options",{".class":"UnionType","items":[{".class":"Instance","args":[{".class":"UnionType","items":["builtins.str","builtins.int","builtins.float"]}],"type_ref":"builtins.list"},{".class":"NoneType"}]}]],"required_keys":["type"]}}},"TextColumn":{".class":"SymbolTableNode","kind":"Gdef","node":{".class":"Decorator","func":{".class":"FuncDef","abstract_status":0,"arg_kinds":[1,5,5,5,5,5,5,5],"arg_names":["label","width","help","disabled","required","default","max_chars","validate"],"dataclass_transform_spec":null,"flags":["is_decorated"],"fullname":"streamlit.elements.lib.column_types.TextColumn","name":"TextColumn","type":{".class":"CallableType","arg_kinds":[1,5,5,5,5,5,5,5],"arg_names":["label","width","help","disabled","required","default","max_chars","validate"],"arg_types":[{".class":"UnionType","items":["builtins.str",{".class":"NoneType"}]},{".class":"UnionType","items":[{".class":"TypeAliasType","args":[],"type_ref":"streamlit.elements.lib.column_types.ColumnWidth"},{".class":"NoneType"}]},{".class":"UnionType","items":["builtins.str",{".class":"NoneType"}]},{".class":"UnionType","items":["builtins.bool",{".class":"NoneType"}]},{".class":"UnionType","items":["builtins.bool",{".class":"NoneType"}]},{".class":"UnionType","items":["builtins.str",{".class":"NoneType"}]},{".class":"UnionType","items":["builtins.int",{".class":"NoneType"}]},{".class":"UnionType","items":["builtins.str",{".class":"NoneType"}]}],"bound_args":[],"def_extras":{"first_arg":null},"fallback":"builtins.function","from_concatenate":false,"implicit":false,"imprecise_arg_kinds":false,"is_ellipsis_args":false,"name":"TextColumn","ret_type":{".class":"TypeAliasType","args":[],"type_ref":"streamlit.elements.lib.column_types.ColumnConfig"},"type_guard":null,"type_is":null,"unpack_kwargs":false,"variables":[]}},"is_overload":false,"var":{".class":"Var","flags":["is_ready","is_inferred"],"fullname":"streamlit.elements.lib.column_types.TextColumn","name":"TextColumn","type":{".class":"CallableType","arg_kinds":[1,5,5,5,5,5,5,5],"arg_names":["label","width","help","disabled","required","default","max_chars","validate"],"arg_types":[{".class":"UnionType","items":["builtins.str",{".class":"NoneType"}]},{".class":"UnionType","items":[{".class":"TypeAliasType","args":[],"type_ref":"streamlit.elements.lib.column_types.ColumnWidth"},{".class":"NoneType"}]},{".class":"UnionType","items":["builtins.str",{".class":"NoneType"}]},{".class":"UnionType","items":["builtins.bool",{".class":"NoneType"}]},{".class":"UnionType","items":["builtins.bool",{".class":"NoneType"}]},{".class":"UnionType","items":["builtins.str",{".class":"NoneType"}]},{".class":"UnionType","items":["builtins.int",{".class":"NoneType"}]},{".class":"UnionType","items":["builtins.str",{".class":"NoneType"}]}],"bound_args":[],"def_extras":{"first_arg":null},"fallback":"builtins.function","from_concatenate":false,"implicit":false,"imprecise_arg_kinds":false,"is_ellipsis_args":false,"name":"TextColumn","ret_type":{".class":"TypeAliasType","args":[],"type_ref":"streamlit.elements.lib.column_types.ColumnConfig"},"type_guard":null,"type_is":null,"unpack_kwargs":false,"variables":[]}}}},"TextColumnConfig":{".class":"SymbolTableNode","kind":"Gdef","node":{".class":"TypeInfo","_promote":[],"abstract_attributes":[],"alt_promote":null,"bases":["typing._TypedDict"],"dataclass_transform_spec":null,"declared_metaclass":null,"defn":{".class":"ClassDef","fullname":"streamlit.elements.lib.column_types.TextColumnConfig","name":"TextColumnConfig","type_vars":[]},"deletable_attributes":[],"flags":[],"fullname":"streamlit.elements.lib.column_types.TextColumnConfig","has_param_spec_type":false,"metaclass_type":null,"metadata":{},"module_name":"streamlit.elements.lib.column_types","mro":["streamlit.elements.lib.column_types.TextColumnConfig","typing._TypedDict","typing.Mapping","typing.Collection","typing.Iterable","typing.Container","builtins.object"],"names":{".class":"SymbolTable"},"self_type":null,"slots":null,"tuple_type":null,"type_vars":[],"typeddict_type":{".class":"TypedDictType","fallback":"typing._TypedDict","items":[["type",{".class":"LiteralType","fallback":"builtins.str","value":"text"}],["max_chars",{".class":"UnionType","items":["builtins.int",{".class":"NoneType"}]}],["validate",{".class":"UnionType","items":["builtins.str",{".class":"NoneType"}]}]],"required_keys":["type"]}}},"TimeColumn":{".class":"SymbolTableNode","kind":"Gdef","node":{".class":"Decorator","func":{".class":"FuncDef","abstract_status":0,"arg_kinds":[1,5,5,5,5,5,5,5,5,5],"arg_names":["label","width","help","disabled","required","default","format","min_value","max_value","step"],"dataclass_transform_spec":null,"flags":["is_decorated"],"fullname":"streamlit.elements.lib.column_types.TimeColumn","name":"TimeColumn","type":{".class":"CallableType","arg_kinds":[1,5,5,5,5,5,5,5,5,5],"arg_names":["label","width","help","disabled","required","default","format","min_value","max_value","step"],"arg_types":[{".class":"UnionType","items":["builtins.str",{".class":"NoneType"}]},{".class":"UnionType","items":[{".class":"TypeAliasType","args":[],"type_ref":"streamlit.elements.lib.column_types.ColumnWidth"},{".class":"NoneType"}]},{".class":"UnionType","items":["builtins.str",{".class":"NoneType"}]},{".class":"UnionType","items":["builtins.bool",{".class":"NoneType"}]},{".class":"UnionType","items":["builtins.bool",{".class":"NoneType"}]},{".class":"UnionType","items":["datetime.time",{".class":"NoneType"}]},{".class":"UnionType","items":["builtins.str",{".class":"NoneType"}]},{".class":"UnionType","items":["datetime.time",{".class":"NoneType"}]},{".class":"UnionType","items":["datetime.time",{".class":"NoneType"}]},{".class":"UnionType","items":["builtins.int","builtins.float","datetime.timedelta",{".class":"NoneType"}]}],"bound_args":[],"def_extras":{"first_arg":null},"fallback":"builtins.function","from_concatenate":false,"implicit":false,"imprecise_arg_kinds":false,"is_ellipsis_args":false,"name":"TimeColumn","ret_type":{".class":"TypeAliasType","args":[],"type_ref":"streamlit.elements.lib.column_types.ColumnConfig"},"type_guard":null,"type_is":null,"unpack_kwargs":false,"variables":[]}},"is_overload":false,"var":{".class":"Var","flags":["is_ready","is_inferred"],"fullname":"streamlit.elements.lib.column_types.TimeColumn","name":"TimeColumn","type":{".class":"CallableType","arg_kinds":[1,5,5,5,5,5,5,5,5,5],"arg_names":["label","width","help","disabled","required","default","format","min_value","max_value","step"],"arg_types":[{".class":"UnionType","items":["builtins.str",{".class":"NoneType"}]},{".class":"UnionType","items":[{".class":"TypeAliasType","args":[],"type_ref":"streamlit.elements.lib.column_types.ColumnWidth"},{".class":"NoneType"}]},{".class":"UnionType","items":["builtins.str",{".class":"NoneType"}]},{".class":"UnionType","items":["builtins.bool",{".class":"NoneType"}]},{".class":"UnionType","items":["builtins.bool",{".class":"NoneType"}]},{".class":"UnionType","items":["datetime.time",{".class":"NoneType"}]},{".class":"UnionType","items":["builtins.str",{".class":"NoneType"}]},{".class":"UnionType","items":["datetime.time",{".class":"NoneType"}]},{".class":"UnionType","items":["datetime.time",{".class":"NoneType"}]},{".class":"UnionType","items":["builtins.int","builtins.float","datetime.timedelta",{".class":"NoneType"}]}],"bound_args":[],"def_extras":{"first_arg":null},"fallback":"builtins.function","from_concatenate":false,"implicit":false,"imprecise_arg_kinds":false,"is_ellipsis_args":false,"name":"TimeColumn","ret_type":{".class":"TypeAliasType","args":[],"type_ref":"streamlit.elements.lib.column_types.ColumnConfig"},"type_guard":null,"type_is":null,"unpack_kwargs":false,"variables":[]}}}},"TimeColumnConfig":{".class":"SymbolTableNode","kind":"Gdef","node":{".class":"TypeInfo","_promote":[],"abstract_attributes":[],"alt_promote":null,"bases":["typing._TypedDict"],"dataclass_transform_spec":null,"declared_metaclass":null,"defn":{".class":"ClassDef","fullname":"streamlit.elements.lib.column_types.TimeColumnConfig","name":"TimeColumnConfig","type_vars":[]},"deletable_attributes":[],"flags":[],"fullname":"streamlit.elements.lib.column_types.TimeColumnConfig","has_param_spec_type":false,"metaclass_type":null,"metadata":{},"module_name":"streamlit.elements.lib.column_types","mro":["streamlit.elements.lib.column_types.TimeColumnConfig","typing._TypedDict","typing.Mapping","typing.Collection","typing.Iterable","typing.Container","builtins.object"],"names":{".class":"SymbolTable"},"self_type":null,"slots":null,"tuple_type":null,"type_vars":[],"typeddict_type":{".class":"TypedDictType","fallback":"typing._TypedDict","items":[["type",{".class":"LiteralType","fallback":"builtins.str","value":"time"}],["format",{".class":"UnionType","items":["builtins.str",{".class":"NoneType"}]}],["min_value",{".class":"UnionType","items":["builtins.str",{".class":"NoneType"}]}],["max_value",{".class":"UnionType","items":["builtins.str",{".class":"NoneType"}]}],["step",{".class":"UnionType","items":["builtins.int","builtins.float",{".class":"NoneType"}]}]],"required_keys":["type"]}}},"TypeAlias":{".class":"SymbolTableNode","cross_ref":"typing.TypeAlias","kind":"Gdef"},"TypedDict":{".class":"SymbolTableNode","cross_ref":"typing.TypedDict","kind":"Gdef"},"__annotations__":{".class":"SymbolTableNode","kind":"Gdef","node":{".class":"Var","flags":["is_ready"],"fullname":"streamlit.elements.lib.column_types.__annotations__","name":"__annotations__","type":{".class":"Instance","args":["builtins.str",{".class":"AnyType","missing_import_name":null,"source_any":null,"type_of_any":6}],"type_ref":"builtins.dict"}}},"__doc__":{".class":"SymbolTableNode","kind":"Gdef","node":{".class":"Var","flags":["is_ready"],"fullname":"streamlit.elements.lib.column_types.__doc__","name":"__doc__","type":"builtins.str"}},"__file__":{".class":"SymbolTableNode","kind":"Gdef","node":{".class":"Var","flags":["is_ready"],"fullname":"streamlit.elements.lib.column_types.__file__","name":"__file__","type":"builtins.str"}},"__name__":{".class":"SymbolTableNode","kind":"Gdef","node":{".class":"Var","flags":["is_ready"],"fullname":"streamlit.elements.lib.column_types.__name__","name":"__name__","type":"builtins.str"}},"__package__":{".class":"SymbolTableNode","kind":"Gdef","node":{".class":"Var","flags":["is_ready"],"fullname":"streamlit.elements.lib.column_types.__package__","name":"__package__","type":"builtins.str"}},"annotations":{".class":"SymbolTableNode","cross_ref":"__future__.annotations","kind":"Gdef"},"datetime":{".class":"SymbolTableNode","cross_ref":"datetime","kind":"Gdef"},"gather_metrics":{".class":"SymbolTableNode","cross_ref":"streamlit.runtime.metrics_util.gather_metrics","kind":"Gdef"}},"path":"/home/zholly/EECS-449-Warm-Up-Assignment/.venv/lib/python3.12/site-packages/streamlit/elements/lib/column_types.py"}